ghsapi/__init__.py
ghsapi/acquisition_api.py
ghsapi/channel_api.py
ghsapi/connection.py
ghsapi/connection_api.py
ghsapi/ghsapi.py
ghsapi/ghsapi_states.py
ghsapi/json_rpc.py
ghsapi/mainframe_api.py
ghsapi/manage_mainframe_settings.py
ghsapi/manage_recordings_api.py
ghsapi/recorder_api.py
ghs_gendaqapi_py-1.1.0.dist-info/LICENSE
ghs_gendaqapi_py-1.1.0.dist-info/METADATA
ghs_gendaqapi_py-1.1.0.dist-info/WHEEL
ghs_gendaqapi_py-1.1.0.dist-info/top_level.txt
ghs_gendaqapi_py-1.1.0.dist-info/RECORD
