Metadata-Version: 2.1
Name: ghs-gendaqapi-py
Version: 1.1.0
Summary: Setup, control and acquire data from the Genesis Highspeed systems via python.
Home-page: https://github.com/hbk-world/ghs-gendaqapi-python
Author: Vishal Goel
Author-email: ext_VGOEL@hbm.com
License: UNKNOWN
Project-URL: Documentation, https://hbk-world.github.io/ghs-gendaqapi-python/html/index.html
Platform: UNKNOWN
Classifier: Programming Language :: Python :: 3
Classifier: License :: OSI Approved :: MIT License
Classifier: Operating System :: OS Independent
Requires-Python: >=3.10
License-File: LICENSE
